gramps_ql/.gitignore
gramps_ql/__init__.py
gramps_ql/_version.py
gramps_ql/gql.py
gramps_ql-0.3.0.dist-info/LICENSE
gramps_ql-0.3.0.dist-info/METADATA
gramps_ql-0.3.0.dist-info/WHEEL
gramps_ql-0.3.0.dist-info/top_level.txt
gramps_ql-0.3.0.dist-info/RECORD
