Metadata-Version: 2.1
Name: gramps-ql
Version: 0.3.0
Summary: A Python library to filter Gramps objects by a query syntax
Author-email: "David M. Straub" <straub@protonmail.com>
License: MIT
Project-URL: homepage, https://github.com/DavidMStraub/gramps-ql
Project-URL: repository, https://github.com/DavidMStraub/gramps-ql
License-File: LICENSE
Requires-Dist: pyparsing >=3
